badam/__init__.py
badam/block_optim.py
badam/utils.py
badam-1.4.dist-info/LICENSE.txt
badam-1.4.dist-info/METADATA
badam-1.4.dist-info/WHEEL
badam-1.4.dist-info/top_level.txt
badam-1.4.dist-info/RECORD
