Metadata-Version: 2.1
Name: badam
Version: 1.4
Summary: Package which implements the algorithm proposed by "BAdam: A Memory Efficient Full Parameter Training Method for Large Language Models".
Home-page: https://github.com/Ledzy/BAdam
Author: Qijun Luo
Author-email: qijunluo@link.cuhk.edu.cn
Project-URL: Bug Tracker, https://github.com/Ledzy/BAdam/issues
Project-URL: Source Code, https://github.com/Ledzy/BAdam
Classifier: Programming Language :: Python :: 3
Classifier: License :: OSI Approved :: MIT License
Classifier: Operating System :: OS Independent
Requires-Python: >=3.7
License-File: LICENSE.txt
Provides-Extra: zero3
Requires-Dist: deepspeed >=0.10.0 ; extra == 'zero3'
